chuk_llm/__init__.py
chuk_llm/chuk_llm.yaml
chuk_llm/cli.py
chuk_llm/client_registry.py
chuk_llm/api/__init__.py
chuk_llm/api/config.py
chuk_llm/api/conversation.py
chuk_llm/api/conversation_sync.py
chuk_llm/api/core.py
chuk_llm/api/discovery.py
chuk_llm/api/dynamic_providers.py
chuk_llm/api/event_loop_manager.py
chuk_llm/api/provider_utils.py
chuk_llm/api/providers.py
chuk_llm/api/session_utils.py
chuk_llm/api/show_info.py
chuk_llm/api/sync.py
chuk_llm/api/tool_execution.py
chuk_llm/api/tool_executor.py
chuk_llm/api/tools.py
chuk_llm/api/utils.py
chuk_llm/configuration/__init__.py
chuk_llm/configuration/models.py
chuk_llm/configuration/unified_config.py
chuk_llm/configuration/validator.py
chuk_llm/core/__init__.py
chuk_llm/core/api_models.py
chuk_llm/core/constants.py
chuk_llm/core/enums.py
chuk_llm/core/json_utils.py
chuk_llm/core/model_capabilities.py
chuk_llm/core/models.py
chuk_llm/core/protocol.py
chuk_llm/llm/__init__.py
chuk_llm/llm/client.py
chuk_llm/llm/connection_pool.py
chuk_llm/llm/features.py
chuk_llm/llm/middleware.py
chuk_llm/llm/system_prompt_generator.py
chuk_llm/llm/core/__init__.py
chuk_llm/llm/core/base.py
chuk_llm/llm/core/errors.py
chuk_llm/llm/core/types.py
chuk_llm/llm/providers/__init__.py
chuk_llm/llm/providers/_config_mixin.py
chuk_llm/llm/providers/_mixins.py
chuk_llm/llm/providers/_tool_compatibility.py
chuk_llm/llm/providers/advantage_client.py
chuk_llm/llm/providers/anthropic_client.py
chuk_llm/llm/providers/azure_openai_client.py
chuk_llm/llm/providers/gemini_client.py
chuk_llm/llm/providers/groq_client.py
chuk_llm/llm/providers/llamacpp_client.py
chuk_llm/llm/providers/llamacpp_server.py
chuk_llm/llm/providers/mistral_client.py
chuk_llm/llm/providers/ollama_client.py
chuk_llm/llm/providers/openai_client.py
chuk_llm/llm/providers/perplexity_client.py
chuk_llm/llm/providers/watsonx_client.py
chuk_llm/media/__init__.py
chuk_llm/media/cli.py
chuk_llm/media/image_gen/__init__.py
chuk_llm/media/image_gen/base.py
chuk_llm-0.17.1.dist-info/licenses/LICENSE
chuk_llm-0.17.1.dist-info/METADATA
chuk_llm-0.17.1.dist-info/WHEEL
chuk_llm-0.17.1.dist-info/entry_points.txt
chuk_llm-0.17.1.dist-info/top_level.txt
chuk_llm-0.17.1.dist-info/RECORD
