Metadata-Version: 2.4
Name: chuk-llm
Version: 0.17.1
Summary: A unified, production-ready Python library for Large Language Model (LLM) providers with real-time streaming, function calling, middleware support, automatic session tracking, dynamic model discovery, and intelligent system prompt generation.
Author-email: Chris Hay <chrishayuk@somejunkmailbox.com>
Maintainer-email: Chris Hay <chrishayuk@somejunkmailbox.com>
License: MIT
Project-URL: Homepage, https://github.com/chrishayuk/chuk-llm
Project-URL: Documentation, https://github.com/chrishayuk/chuk-llm#readme
Project-URL: Repository, https://github.com/chrishayuk/chuk-llm.git
Project-URL: Issues, https://github.com/chrishayuk/chuk-llm/issues
Project-URL: Changelog, https://github.com/chrishayuk/chuk-llm/releases
Keywords: llm,ai,openai,anthropic,claude,gpt,gemini,ollama,streaming,async,machine-learning
Classifier: Development Status :: 4 - Beta
Classifier: Intended Audience :: Developers
Classifier: License :: OSI Approved :: MIT License
Classifier: Operating System :: OS Independent
Classifier: Programming Language :: Python :: 3
Classifier: Programming Language :: Python :: 3.11
Classifier: Programming Language :: Python :: 3.12
Classifier: Topic :: Software Development :: Libraries :: Python Modules
Classifier: Topic :: Scientific/Engineering :: Artificial Intelligence
Classifier: Typing :: Typed
Requires-Python: >=3.11
License-File: LICENSE
Requires-Dist: aiohttp>=3.12.15
Requires-Dist: anthropic>=0.62.0
Requires-Dist: asyncio>=4.0.0
Requires-Dist: chuk-ai-session-manager>=0.7
Requires-Dist: google-genai>=1.29.0
Requires-Dist: groq>=0.25.0
Requires-Dist: httpx>=0.28.1
Requires-Dist: ibm-watsonx-ai>=1.3.30
Requires-Dist: jinja2>=3.1.6
Requires-Dist: mistralai>=1.9.3
Requires-Dist: ollama>=0.5.3
Requires-Dist: openai>=1.79.0
Requires-Dist: python-dotenv>=1.1.0
Requires-Dist: pyyaml>=6.0.2
Requires-Dist: tiktoken>=0.11.0
Requires-Dist: transformers>=4.53.2
Requires-Dist: ujson>=5.11.0
Provides-Extra: redis
Requires-Dist: chuk-ai-session-manager[redis]>=0.7; extra == "redis"
Provides-Extra: watsonx
Requires-Dist: ibm-watsonx-ai; extra == "watsonx"
Requires-Dist: jinja2>=3.1.6; extra == "watsonx"
Requires-Dist: transformers>=4.53.2; extra == "watsonx"
Provides-Extra: cli
Requires-Dist: rich>=14.0.0; extra == "cli"
Provides-Extra: dev
Requires-Dist: pytest-asyncio>=0.26.0; extra == "dev"
Requires-Dist: pytest>=8.3.5; extra == "dev"
Requires-Dist: pytest-cov>=6.1.1; extra == "dev"
Requires-Dist: rich>=14.0.0; extra == "dev"
Requires-Dist: orjson>=3.10.0; extra == "dev"
Requires-Dist: ujson>=5.10.0; extra == "dev"
Provides-Extra: all
Requires-Dist: chuk-ai-session-manager[redis]>=0.7; extra == "all"
Requires-Dist: rich>=14.0.0; extra == "all"
Dynamic: license-file
